diffusion_models/__init__.py
diffusion_models/diffusion_inference.py
diffusion_models/diffusion_trainer.py
diffusion_models/gaussian_diffusion/__init__.py
diffusion_models/gaussian_diffusion/base_diffuser.py
diffusion_models/gaussian_diffusion/beta_schedulers.py
diffusion_models/gaussian_diffusion/ddimm_diffuser.py
diffusion_models/gaussian_diffusion/gaussian_diffuser.py
diffusion_models/models/SimpleUnet.py
diffusion_models/models/__init__.py
diffusion_models/models/base_diffusion_model.py
diffusion_models/utils/__init__.py
diffusion_models/utils/schemas.py
diffusion_models/utils/tensorboard.py
diffusion_model_framework-1.0.2.dist-info/METADATA
diffusion_model_framework-1.0.2.dist-info/WHEEL
diffusion_model_framework-1.0.2.dist-info/RECORD
