Metadata-Version: 2.1
Name: diffusion-model-framework
Version: 1.0.2
Summary: 
Home-page: https://github.com/sachahu1/Diffusion-Model-Framework
Author: Sacha Hu
Author-email: sachahu@mindsparkai.com
Requires-Python: >=3.10,<3.13
Classifier: Programming Language :: Python :: 3
Classifier: Programming Language :: Python :: 3.10
Classifier: Programming Language :: Python :: 3.11
Classifier: Programming Language :: Python :: 3.12
Requires-Dist: numpy (>=2.1.3,<3.0.0)
Requires-Dist: pillow (>=11.0.0,<12.0.0)
Requires-Dist: tensorboard (>=2.18.0,<3.0.0)
Requires-Dist: torch (>=2.5.1,<3.0.0)
Requires-Dist: torchvision (>=0.20.1,<0.21.0)
Requires-Dist: tqdm (>=4.66.2,<5.0.0)
Requires-Dist: transformers (>=4.46.1,<5.0.0)
Project-URL: Documentation, https://www.sachahu.com/docs/diffusion-model-framework/latest/index.html
Project-URL: Repository, https://github.com/sachahu1/Diffusion-Model-Framework
